5to Semestre/arquitecturaDeComputadoras/practica04/circuito.vhd
-- Rotador/barrel shifter de 4 bits con when/else.
-- ctrl = "00": sin cambio, "01": corrimiento derecha con 0,
-- "10": corrimiento izquierda con 0, "11": rotacion izquierda.
library IEEE;
use IEEE.STD_LOGIC_1164.all;

entity shift_when_23400357 is
  port (
    ent  : in  STD_LOGIC_VECTOR(3 downto 0);
    ctrl : in  STD_LOGIC_VECTOR(1 downto 0);
    sal  : out STD_LOGIC_VECTOR(3 downto 0)
  );
end shift_when_23400357;

architecture arqui_shift_when_23400357 of shift_when_23400357 is
begin
  sal <= (ent)                          when (ctrl = "00") else
         ('0' & ent(3 downto 1))        when (ctrl = "01") else
         (ent(2 downto 0) & '0')        when (ctrl = "10") else
         (ent(0) & ent(1) & ent(2) & ent(3)) when (ctrl = "11") else
         "----";
end arqui_shift_when_23400357;

5to Semestre/arquitecturaDeComputadoras/practica04/tb_circuito.vhd
library IEEE;
use IEEE.STD_LOGIC_1164.all;
use IEEE.NUMERIC_STD.all;

entity tb_circuito is
end tb_circuito;

architecture t of tb_circuito is
  signal ent  : STD_LOGIC_VECTOR(3 downto 0) := (others => '0');
  signal ctrl : STD_LOGIC_VECTOR(1 downto 0) := (others => '0');
  signal sal  : STD_LOGIC_VECTOR(3 downto 0);
begin

  uut : entity work.shift_when_23400357(arqui_shift_when_23400357)
        port map (ent, ctrl, sal);

  stim : process
  begin
    -- Solo ctrl="00" con todas las entradas, para ver el bus entero.
    for i in 0 to 15 loop
      ent <= STD_LOGIC_VECTOR(to_unsigned(i, 4));
      ctrl <= "00";
      wait for 100 ns;
    end loop;

    -- Un patron fijo (1010) con los 4 controles, para ver los shift/rot.
    for i in 0 to 3 loop
      ent  <= "1010";
      ctrl <= STD_LOGIC_VECTOR(to_unsigned(i, 2));
      wait for 100 ns;
    end loop;

    report "Listo: 16 + 4 combinaciones aplicadas. Abre el .vcd en gtkwave.";
    wait;
  end process;

end t;

5to Semestre/arquitecturaDeComputadoras/practica04/tb_circuito.vcd
$date
  Sat Sep 12 15:42:49 2026
$end
$version
  GHDL v0
$end
$timescale
  1 fs
$end
$scope module standard $end
$upscope $end
$scope module std_logic_1164 $end
$upscope $end
$scope module numeric_std $end
$upscope $end
$scope module tb_circuito $end
$var reg 4 ! ent[3:0] $end
$var reg 2 " ctrl[1:0] $end
$var reg 4 # sal[3:0] $end
$scope module uut $end
$var reg 4 $ ent[3:0] $end
$var reg 2 % ctrl[1:0] $end
$var reg 4 & sal[3:0] $end
$upscope $end
$upscope $end
$enddefinitions $end
#0
b0000 !
b00 "
b0000 #
b0000 $
b00 %
b0000 &
#100000000
b0001 !
b0001 #
b0001 $
b0001 &
#200000000
b0010 !
b0010 #
b0010 $
b0010 &
#300000000
b0011 !
b0011 #
b0011 $
b0011 &
#400000000
b0100 !
b0100 #
b0100 $
b0100 &
#500000000
b0101 !
b0101 #
b0101 $
b0101 &
#600000000
b0110 !
b0110 #
b0110 $
b0110 &
#700000000
b0111 !
b0111 #
b0111 $
b0111 &
#800000000
b1000 !
b1000 #
b1000 $
b1000 &
#900000000
b1001 !
b1001 #
b1001 $
b1001 &
#1000000000
b1010 !
b1010 #
b1010 $
b1010 &
#1100000000
b1011 !
b1011 #
b1011 $
b1011 &
#1200000000
b1100 !
b1100 #
b1100 $
b1100 &
#1300000000
b1101 !
b1101 #
b1101 $
b1101 &
#1400000000
b1110 !
b1110 #
b1110 $
b1110 &
#1500000000
b1111 !
b1111 #
b1111 $
b1111 &
#1600000000
b1010 !
b1010 #
b1010 $
b1010 &
#1700000000
b01 "
b0101 #
b01 %
b0101 &
#1800000000
b10 "
b0100 #
b10 %
b0100 &
#1900000000
b11 "
b0101 #
b11 %
b0101 &
