5to Semestre/arquitecturaDeComputadoras/practica07/circuito.vhd
-- Practica 7: multiplexor 4x1 con logica en cada canal (el diagrama del profe).
--
-- Idea: hay 9 entradas ent(0)..ent(8), un selector s(1 downto 0) y una salida
-- sal. Primero se calcula el valor de cada uno de los 4 canales con sus
-- compuertas, y luego el mux 4x1 elige UNO de esos 4 segun s.
--
-- Canal 00: ent(0) pasa por un inversor y luego un OR con ent(1)
--           c0 = ent(0)' + ent(1)
-- Canal 01: NOR de 3 entradas (ent(2),ent(3),ent(4)); su salida entra a una
--           NAND de 2 junto con ent(5)
--           c1 = ((ent(2) + ent(3) + ent(4))' * ent(5))'
-- Canal 10: dos AND alimentando un OR
--           c2 = (ent(5) * ent(6)) + (ent(7) * ent(8))
-- Canal 11: AND de 3 entradas (ent5,ent6,ent7); su salida a una XOR con ent(8)
--           c3 = (ent(5) * ent(6) * ent(7)) XOR ent(8)
--
-- sal = c0 si s="00", c1 si s="01", c2 si s="10", c3 si s="11".
library IEEE;
use IEEE.STD_LOGIC_1164.all;

entity mux4x1_logica_23400357 is
  port (
    ent : in  STD_LOGIC_VECTOR(8 downto 0);  -- ent(0)..ent(8)
    s   : in  STD_LOGIC_VECTOR(1 downto 0);  -- selector: 00,01,10,11
    sal : out STD_LOGIC                      -- salida del mux
  );
end mux4x1_logica_23400357;

-- ESTILO 1: tal cual el diagrama, compuerta por compuerta.
architecture estructural of mux4x1_logica_23400357 is
  signal c0, c1, c2, c3   : STD_LOGIC;
  signal n0, nor234       : STD_LOGIC;
  signal a56, a78, a567   : STD_LOGIC;
begin
  -- canal 00
  n0  <= not ent(0);
  c0  <= n0 or ent(1);

  -- canal 01: NOR de 3 y luego NAND con ent(5)
  nor234 <= not (ent(2) or ent(3) or ent(4));
  c1  <= nor234 nand ent(5);

  -- canal 10
  a56 <= ent(5) and ent(6);
  a78 <= ent(7) and ent(8);
  c2  <= a56 or a78;

  -- canal 11: AND de 3 y luego XOR con ent(8)
  a567 <= ent(5) and ent(6) and ent(7);
  c3  <= a567 xor ent(8);

  -- mux 4x1
  with s select
    sal <= c0 when "00",
           c1 when "01",
           c2 when "10",
           c3 when others;
end estructural;

-- ESTILO 2: todo en una expresion concurrente, sin senales intermedias.
-- Equivalente al estructural (las senales de arriba solo dan claridad).
architecture simplificada of mux4x1_logica_23400357 is
begin
  with s select
    sal <= ((not ent(0)) or ent(1))                                       when "00",
           (not ((not (ent(2) or ent(3) or ent(4))) and ent(5)))          when "01",
           ((ent(5) and ent(6)) or (ent(7) and ent(8)))                   when "10",
           ((ent(5) and ent(6) and ent(7)) xor ent(8))                    when others;
end simplificada;

5to Semestre/arquitecturaDeComputadoras/practica07/tb_circuito.vhd
-- Testbench: barre las 4 posiciones del selector y las 512 combinaciones de
-- las 9 entradas (2048 casos) y COMPRUEBA la salida contra un modelo calculado
-- con las MISMAS expresiones, y ademas que la version estructural y la
-- simplificada coincidan. Asi el circuito se autoverifica: si algo se rompe,
-- la simulacion falla sola.
library IEEE;
use IEEE.STD_LOGIC_1164.all;
use IEEE.NUMERIC_STD.all;

entity tb_circuito is
end tb_circuito;

architecture t of tb_circuito is
  signal ent : STD_LOGIC_VECTOR(8 downto 0) := (others => '0');
  signal s   : STD_LOGIC_VECTOR(1 downto 0) := "00";
  signal sal_est, sal_sim : STD_LOGIC;
begin

  -- Dos instancias: la del diagrama (estructural) y la de una linea (simplificada).
  uut_est : entity work.mux4x1_logica_23400357(estructural)
            port map (ent, s, sal_est);
  uut_sim : entity work.mux4x1_logica_23400357(simplificada)
            port map (ent, s, sal_sim);

  stim : process
    variable c0, c1, c2, c3, esperado : STD_LOGIC;
    variable e : STD_LOGIC_VECTOR(8 downto 0);
    variable fallos : integer := 0;
  begin
    -- Recorre las 4 opciones del selector y las 512 combinaciones de entradas.
    for k in 0 to 3 loop
      s <= STD_LOGIC_VECTOR(to_unsigned(k, 2));
      for i in 0 to 511 loop
        e := STD_LOGIC_VECTOR(to_unsigned(i, 9));
        ent <= e;
        wait for 1 ns;

        -- Modelo de referencia: las expresiones del diagrama.
        c0 := (not e(0)) or e(1);
        c1 := not ((not (e(2) or e(3) or e(4))) and e(5));
        c2 := (e(5) and e(6)) or (e(7) and e(8));
        c3 := (e(5) and e(6) and e(7)) xor e(8);

        case k is
          when 0    => esperado := c0;
          when 1    => esperado := c1;
          when 2    => esperado := c2;
          when others => esperado := c3;
        end case;

        -- Las dos arquitecturas deben dar lo mismo que el modelo.
        assert sal_est = esperado
          report "estructural: caso " & integer'image(i) & " s="
               & integer'image(k) & " dio " & STD_LOGIC'image(sal_est)
          severity error;
        assert sal_sim = esperado
          report "simplificada: caso " & integer'image(i) & " s="
               & integer'image(k) & " dio " & STD_LOGIC'image(sal_sim)
          severity error;

        if (sal_est /= esperado) or (sal_sim /= esperado) then
          fallos := fallos + 1;
        end if;
      end loop;
    end loop;

    assert fallos = 0 report "Fallaron " & integer'image(fallos) & " casos."
      severity failure;
    report "OK: 4 selectores x 512 combinaciones = 2048 casos correctos.";
    wait;
  end process;

end t;

5to Semestre/arquitecturaDeComputadoras/practica07/tb_circuito.vcd
$date
  Fri Sep 25 23:51:13 2026
$end
$version
  GHDL v0
$end
$timescale
  1 fs
$end
$scope module standard $end
$upscope $end
$scope module std_logic_1164 $end
$upscope $end
$scope module numeric_std $end
$upscope $end
$scope module tb_circuito $end
$var reg 9 ! ent[8:0] $end
$var reg 2 " s[1:0] $end
$var reg 1 # sal_est $end
$var reg 1 $ sal_sim $end
$scope module uut_est $end
$var reg 9 % ent[8:0] $end
$var reg 2 & s[1:0] $end
$var reg 1 ' sal $end
$var reg 1 ( c0 $end
$var reg 1 ) c1 $end
$var reg 1 * c2 $end
$var reg 1 + c3 $end
$var reg 1 , n0 $end
$var reg 1 - nor234 $end
$var reg 1 . a56 $end
$var reg 1 / a78 $end
$var reg 1 0 a567 $end
$upscope $end
$scope module uut_sim $end
$var reg 9 1 ent[8:0] $end
$var reg 2 2 s[1:0] $end
$var reg 1 3 sal $end
$upscope $end
$upscope $end
$enddefinitions $end
#0
b000000000 !
b00 "
1#
1$
b000000000 %
b00 &
1'
1(
1)
0*
0+
1,
1-
0.
0/
00
b000000000 1
b00 2
13
#1000000
b000000001 !
0#
0$
b000000001 %
0'
0(
0,
b000000001 1
03
#2000000
b000000010 !
1#
1$
b000000010 %
1'
1(
1,
b000000010 1
13
#3000000
b000000011 !
b000000011 %
0,
b000000011 1
#4000000
b000000100 !
1#
b000000100 %
1'
1(
1,
0-
b000000100 1
#5000000
b000000101 !
0#
0$
b000000101 %
0'
0(
0,
b000000101 1
03
#6000000
b000000110 !
1#
1$
b000000110 %
1'
1(
1,
b000000110 1
13
#7000000
b000000111 !
b000000111 %
0,
b000000111 1
#8000000
b000001000 !
1#
b000001000 %
1'
1(
1,
b000001000 1
#9000000
b000001001 !
0#
0$
b000001001 %
0'
0(
0,
b000001001 1
03
#10000000
b000001010 !
1#
1$
b000001010 %
1'
1(
1,
b000001010 1
13
#11000000
b000001011 !
b000001011 %
0,
b000001011 1
#12000000
b000001100 !
1#
b000001100 %
1'
1(
1,
b000001100 1
#13000000
b000001101 !
0#
0$
b000001101 %
0'
0(
0,
b000001101 1
03
#14000000
b000001110 !
1#
1$
b000001110 %
1'
1(
1,
b000001110 1
13
#15000000
b000001111 !
b000001111 %
0,
b000001111 1
#16000000
b000010000 !
1#
b000010000 %
1'
1(
1,
b000010000 1
#17000000
b000010001 !
0#
0$
b000010001 %
0'
0(
0,
b000010001 1
03
#18000000
b000010010 !
1#
1$
b000010010 %
1'
1(
1,
b000010010 1
13
#19000000
b000010011 !
b000010011 %
0,
b000010011 1
#20000000
b000010100 !
1#
b000010100 %
1'
1(
1,
b000010100 1
#21000000
b000010101 !
0#
0$
b000010101 %
0'
0(
0,
b000010101 1
03
#22000000
b000010110 !
1#
1$
b000010110 %
1'
1(
1,
b000010110 1
13
#23000000
b000010111 !
b000010111 %
0,
b000010111 1
#24000000
b000011000 !
1#
b000011000 %
1'
1(
1,
b000011000 1
#25000000
b000011001 !
0#
0$
b000011001 %
0'
0(
0,
b000011001 1
03
#26000000
b000011010 !
1#
1$
b000011010 %
1'
1(
1,
b000011010 1
13
#27000000
b000011011 !
b000011011 %
0,
b000011011 1
#28000000
b000011100 !
1#
b000011100 %
1'
1(
1,
b000011100 1
#29000000
b000011101 !
0#
0$
b000011101 %
0'
0(
0,
b000011101 1
03
#30000000
b000011110 !
1#
1$
b000011110 %
1'
1(
1,
b000011110 1
13
#31000000
b000011111 !
b000011111 %
0,
b000011111 1
#32000000
b000100000 !
1#
b000100000 %
1'
1(
0)
1,
1-
b000100000 1
#33000000
b000100001 !
0#
0$
b000100001 %
0'
0(
0,
b000100001 1
03
#34000000
b000100010 !
1#
1$
b000100010 %
1'
1(
1,
b000100010 1
13
#35000000
b000100011 !
b000100011 %
0,
b000100011 1
#36000000
b000100100 !
1#
b000100100 %
1'
1(
1)
1,
0-
b000100100 1
#37000000
b000100101 !
0#
0$
b000100101 %
0'
0(
0,
b000100101 1
03
#38000000
b000100110 !
1#
1$
b000100110 %
1'
1(
1,
b000100110 1
13
#39000000
b000100111 !
b000100111 %
0,
b000100111 1
#40000000
b000101000 !
1#
b000101000 %
1'
1(
1,
b000101000 1
#41000000
b000101001 !
0#
0$
b000101001 %
0'
0(
0,
b000101001 1
03
#42000000
b000101010 !
1#
1$
b000101010 %
1'
1(
1,
b000101010 1
13
#43000000
b000101011 !
b000101011 %
0,
b000101011 1
#44000000
b000101100 !
1#
b000101100 %
1'
1(
1,
b000101100 1
#45000000
b000101101 !
0#
0$
b000101101 %
0'
0(
0,
b000101101 1
03
#46000000
b000101110 !
1#
1$
b000101110 %
1'
1(
1,
b000101110 1
13
#47000000
b000101111 !
b000101111 %
0,
b000101111 1
#48000000
b000110000 !
1#
b000110000 %
1'
1(
1,
b000110000 1
#49000000
b000110001 !
0#
0$
b000110001 %
0'
0(
0,
b000110001 1
03
#50000000
b000110010 !
1#
1$
b000110010 %
1'
1(
1,
b000110010 1
13
#51000000
b000110011 !
b000110011 %
0,
b000110011 1
#52000000
b000110100 !
1#
b000110100 %
1'
1(
1,
b000110100 1
#53000000
b000110101 !
0#
0$
b000110101 %
0'
0(
0,
b000110101 1
03
#54000000
b000110110 !
1#
1$
b000110110 %
1'
1(
1,
b000110110 1
13
#55000000
b000110111 !
b000110111 %
0,
b000110111 1
#56000000
b000111000 !
1#
b000111000 %
1'
1(
1,
b000111000 1
#57000000
b000111001 !
0#
0$
b000111001 %
0'
0(
0,
b000111001 1
03
#58000000
b000111010 !
1#
1$
b000111010 %
1'
1(
1,
b000111010 1
13
#59000000
b000111011 !
b000111011 %
0,
b000111011 1
#60000000
b000111100 !
1#
b000111100 %
1'
1(
1,
b000111100 1
#61000000
b000111101 !
0#
0$
b000111101 %
0'
0(
0,
b000111101 1
03
#62000000
b000111110 !
1#
1$
b000111110 %
1'
1(
1,
b000111110 1
13
#63000000
b000111111 !
b000111111 %
0,
b000111111 1
#64000000
b001000000 !
1#
b001000000 %
1'
1(
1,
1-
b001000000 1
#65000000
b001000001 !
0#
0$
b001000001 %
0'
0(
0,
b001000001 1
03
#66000000
b001000010 !
1#
1$
b001000010 %
1'
1(
1,
b001000010 1
13
#67000000
b001000011 !
b001000011 %
0,
b001000011 1
#68000000
b001000100 !
1#
b001000100 %
1'
1(
1,
0-
b001000100 1
#69000000
b001000101 !
0#
0$
b001000101 %
0'
0(
0,
b001000101 1
03
#70000000
b001000110 !
1#
1$
b001000110 %
1'
1(
1,
b001000110 1
13
#71000000
b001000111 !
b001000111 %
0,
b001000111 1
#72000000
b001001000 !
1#
b001001000 %
1'
1(
1,
b001001000 1
#73000000
b001001001 !
0#
0$
b001001001 %
0'
0(
0,
b001001001 1
03
#74000000
b001001010 !
1#
1$
b001001010 %
1'
1(
1,
b001001010 1
13
#75000000
b001001011 !
b001001011 %
0,
b001001011 1
#76000000
b001001100 !
1#
b001001100 %
1'
1(
1,
b001001100 1
#77000000
b001001101 !
0#
0$
b001001101 %
0'
0(
0,
b001001101 1
03
#78000000
b001001110 !
1#
1$
b001001110 %
1'
1(
1,
b001001110 1
13
#79000000
b001001111 !
b001001111 %
0,
b001001111 1
#80000000
b001010000 !
1#
b001010000 %
1'
1(
1,
b001010000 1
#81000000
b001010001 !
0#
0$
b001010001 %
0'
0(
0,
b001010001 1
03
#82000000
b001010010 !
1#
1$
b001010010 %
1'
1(
1,
b001010010 1
13
#83000000
b001010011 !
b001010011 %
0,
b001010011 1
#84000000
b001010100 !
1#
b001010100 %
1'
1(
1,
b001010100 1
#85000000
b001010101 !
0#
0$
b001010101 %
0'
0(
0,
b001010101 1
03
#86000000
b001010110 !
1#
1$
b001010110 %
1'
1(
1,
b001010110 1
13
#87000000
b001010111 !
b001010111 %
0,
b001010111 1
#88000000
b001011000 !
1#
b001011000 %
1'
1(
1,
b001011000 1
#89000000
b001011001 !
0#
0$
b001011001 %
0'
0(
0,
b001011001 1
03
#90000000
b001011010 !
1#
1$
b001011010 %
1'
1(
1,
b001011010 1
13
#91000000
b001011011 !
b001011011 %
0,
b001011011 1
#92000000
b001011100 !
1#
b001011100 %
1'
1(
1,
b001011100 1
#93000000
b001011101 !
0#
0$
b001011101 %
0'
0(
0,
b001011101 1
03
#94000000
b001011110 !
1#
1$
b001011110 %
1'
1(
1,
b001011110 1
13
#95000000
b001011111 !
b001011111 %
0,
b001011111 1
#96000000
b001100000 !
1#
b001100000 %
1'
1(
0)
1*
1,
1-
1.
b001100000 1
#97000000
b001100001 !
0#
0$
b001100001 %
0'
0(
0,
b001100001 1
03
#98000000
b001100010 !
1#
1$
b001100010 %
1'
1(
1,
b001100010 1
13
#99000000
b001100011 !
b001100011 %
0,
b001100011 1
#100000000
b001100100 !
1#
b001100100 %
1'
1(
1)
1,
0-
b001100100 1
#101000000
b001100101 !
0#
0$
b001100101 %
0'
0(
0,
b001100101 1
03
#102000000
b001100110 !
1#
1$
b001100110 %
1'
1(
1,
b001100110 1
13
#103000000
b001100111 !
b001100111 %
0,
b001100111 1
#104000000
b001101000 !
1#
b001101000 %
1'
1(
1,
b001101000 1
#105000000
b001101001 !
0#
0$
b001101001 %
0'
0(
0,
b001101001 1
03
#106000000
b001101010 !
1#
1$
b001101010 %
1'
1(
1,
b001101010 1
13
#107000000
b001101011 !
b001101011 %
0,
b001101011 1
#108000000
b001101100 !
1#
b001101100 %
1'
1(
1,
b001101100 1
#109000000
b001101101 !
0#
0$
b001101101 %
0'
0(
0,
b001101101 1
03
#110000000
b001101110 !
1#
1$
b001101110 %
1'
1(
1,
b001101110 1
13
#111000000
b001101111 !
b001101111 %
0,
b001101111 1
#112000000
b001110000 !
1#
b001110000 %
1'
1(
1,
b001110000 1
#113000000
b001110001 !
0#
0$
b001110001 %
0'
0(
0,
b001110001 1
03
#114000000
b001110010 !
1#
1$
b001110010 %
1'
1(
1,
b001110010 1
13
#115000000
b001110011 !
b001110011 %
0,
b001110011 1
#116000000
b001110100 !
1#
b001110100 %
1'
1(
1,
b001110100 1
#117000000
b001110101 !
0#
0$
b001110101 %
0'
0(
0,
b001110101 1
03
#118000000
b001110110 !
1#
1$
b001110110 %
1'
1(
1,
b001110110 1
13
#119000000
b001110111 !
b001110111 %
0,
b001110111 1
#120000000
b001111000 !
1#
b001111000 %
1'
1(
1,
b001111000 1
#121000000
b001111001 !
0#
0$
b001111001 %
0'
0(
0,
b001111001 1
03
#122000000
b001111010 !
1#
1$
b001111010 %
1'
1(
1,
b001111010 1
13
#123000000
b001111011 !
b001111011 %
0,
b001111011 1
#124000000
b001111100 !
1#
b001111100 %
1'
1(
1,
b001111100 1
#125000000
b001111101 !
0#
0$
b001111101 %
0'
0(
0,
b001111101 1
03
#126000000
b001111110 !
1#
1$
b001111110 %
1'
1(
1,
b001111110 1
13
#127000000
b001111111 !
b001111111 %
0,
b001111111 1
#128000000
b010000000 !
1#
b010000000 %
1'
1(
0*
1,
1-
0.
b010000000 1
#129000000
b010000001 !
0#
0$
b010000001 %
0'
0(
0,
b010000001 1
03
#130000000
b010000010 !
1#
1$
b010000010 %
1'
1(
1,
b010000010 1
13
#131000000
b010000011 !
b010000011 %
0,
b010000011 1
#132000000
b010000100 !
1#
b010000100 %
1'
1(
1,
0-
b010000100 1
#133000000
b010000101 !
0#
0$
b010000101 %
0'
0(
0,
b010000101 1
03
#134000000
b010000110 !
1#
1$
b010000110 %
1'
1(
1,
b010000110 1
13
#135000000
b010000111 !
b010000111 %
0,
b010000111 1
#136000000
b010001000 !
1#
b010001000 %
1'
1(
1,
b010001000 1
#137000000
b010001001 !
0#
0$
b010001001 %
0'
0(
0,
b010001001 1
03
#138000000
b010001010 !
1#
1$
b010001010 %
1'
1(
1,
b010001010 1
13
#139000000
b010001011 !
b010001011 %
0,
b010001011 1
#140000000
b010001100 !
1#
b010001100 %
1'
1(
1,
b010001100 1
#141000000
b010001101 !
0#
0$
b010001101 %
0'
0(
0,
b010001101 1
03
#142000000
b010001110 !
1#
1$
b010001110 %
1'
1(
1,
b010001110 1
13
#143000000
b010001111 !
b010001111 %
0,
b010001111 1
#144000000
b010010000 !
1#
b010010000 %
1'
1(
1,
b010010000 1
#145000000
b010010001 !
0#
0$
b010010001 %
0'
0(
0,
b010010001 1
03
#146000000
b010010010 !
1#
1$
b010010010 %
1'
1(
1,
b010010010 1
13
#147000000
b010010011 !
b010010011 %
0,
b010010011 1
#148000000
b010010100 !
1#
b010010100 %
1'
1(
1,
b010010100 1
#149000000
b010010101 !
0#
0$
b010010101 %
0'
0(
0,
b010010101 1
03
#150000000
b010010110 !
1#
1$
b010010110 %
1'
1(
1,
b010010110 1
13
#151000000
b010010111 !
b010010111 %
0,
b010010111 1
#152000000
b010011000 !
1#
b010011000 %
1'
1(
1,
b010011000 1
#153000000
b010011001 !
0#
0$
b010011001 %
0'
0(
0,
b010011001 1
03
#154000000
b010011010 !
1#
1$
b010011010 %
1'
1(
1,
b010011010 1
13
#155000000
b010011011 !
b010011011 %
0,
b010011011 1
#156000000
b010011100 !
1#
b010011100 %
1'
1(
1,
b010011100 1
#157000000
b010011101 !
0#
0$
b010011101 %
0'
0(
0,
b010011101 1
03
#158000000
b010011110 !
1#
1$
b010011110 %
1'
1(
1,
b010011110 1
13
#159000000
b010011111 !
b010011111 %
0,
b010011111 1
#160000000
b010100000 !
1#
b010100000 %
1'
1(
0)
1,
1-
b010100000 1
#161000000
b010100001 !
0#
0$
b010100001 %
0'
0(
0,
b010100001 1
03
#162000000
b010100010 !
1#
1$
b010100010 %
1'
1(
1,
b010100010 1
13
#163000000
b010100011 !
b010100011 %
0,
b010100011 1
#164000000
b010100100 !
1#
b010100100 %
1'
1(
1)
1,
0-
b010100100 1
#165000000
b010100101 !
0#
0$
b010100101 %
0'
0(
0,
b010100101 1
03
#166000000
b010100110 !
1#
1$
b010100110 %
1'
1(
1,
b010100110 1
13
#167000000
b010100111 !
b010100111 %
0,
b010100111 1
#168000000
b010101000 !
1#
b010101000 %
1'
1(
1,
b010101000 1
#169000000
b010101001 !
0#
0$
b010101001 %
0'
0(
0,
b010101001 1
03
#170000000
b010101010 !
1#
1$
b010101010 %
1'
1(
1,
b010101010 1
13
#171000000
b010101011 !
b010101011 %
0,
b010101011 1
#172000000
b010101100 !
1#
b010101100 %
1'
1(
1,
b010101100 1
#173000000
b010101101 !
0#
0$
b010101101 %
0'
0(
0,
b010101101 1
03
#174000000
b010101110 !
1#
1$
b010101110 %
1'
1(
1,
b010101110 1
13
#175000000
b010101111 !
b010101111 %
0,
b010101111 1
#176000000
b010110000 !
1#
b010110000 %
1'
1(
1,
b010110000 1
#177000000
b010110001 !
0#
0$
b010110001 %
0'
0(
0,
b010110001 1
03
#178000000
b010110010 !
1#
1$
b010110010 %
1'
1(
1,
b010110010 1
13
#179000000
b010110011 !
b010110011 %
0,
b010110011 1
#180000000
b010110100 !
1#
b010110100 %
1'
1(
1,
b010110100 1
#181000000
b010110101 !
0#
0$
b010110101 %
0'
0(
0,
b010110101 1
03
#182000000
b010110110 !
1#
1$
b010110110 %
1'
1(
1,
b010110110 1
13
#183000000
b010110111 !
b010110111 %
0,
b010110111 1
#184000000
b010111000 !
1#
b010111000 %
1'
1(
1,
b010111000 1
#185000000
b010111001 !
0#
0$
b010111001 %
0'
0(
0,
b010111001 1
03
#186000000
b010111010 !
1#
1$
b010111010 %
1'
1(
1,
b010111010 1
13
#187000000
b010111011 !
b010111011 %
0,
b010111011 1
#188000000
b010111100 !
1#
b010111100 %
1'
1(
1,
b010111100 1
#189000000
b010111101 !
0#
0$
b010111101 %
0'
0(
0,
b010111101 1
03
#190000000
b010111110 !
1#
1$
b010111110 %
1'
1(
1,
b010111110 1
13
#191000000
b010111111 !
b010111111 %
0,
b010111111 1
#192000000
b011000000 !
1#
b011000000 %
1'
1(
1,
1-
b011000000 1
#193000000
b011000001 !
0#
0$
b011000001 %
0'
0(
0,
b011000001 1
03
#194000000
b011000010 !
1#
1$
b011000010 %
1'
1(
1,
b011000010 1
13
#195000000
b011000011 !
b011000011 %
0,
b011000011 1
#196000000
b011000100 !
1#
b011000100 %
1'
1(
1,
0-
b011000100 1
#197000000
b011000101 !
0#
0$
b011000101 %
0'
0(
0,
b011000101 1
03
#198000000
b011000110 !
1#
1$
b011000110 %
1'
1(
1,
b011000110 1
13
#199000000
b011000111 !
b011000111 %
0,
b011000111 1
#200000000
b011001000 !
1#
b011001000 %
1'
1(
1,
b011001000 1
#201000000
b011001001 !
0#
0$
b011001001 %
0'
0(
0,
b011001001 1
03
#202000000
b011001010 !
1#
1$
b011001010 %
1'
1(
1,
b011001010 1
13
#203000000
b011001011 !
b011001011 %
0,
b011001011 1
#204000000
b011001100 !
1#
b011001100 %
1'
1(
1,
b011001100 1
#205000000
b011001101 !
0#
0$
b011001101 %
0'
0(
0,
b011001101 1
03
#206000000
b011001110 !
1#
1$
b011001110 %
1'
1(
1,
b011001110 1
13
#207000000
b011001111 !
b011001111 %
0,
b011001111 1
#208000000
b011010000 !
1#
b011010000 %
1'
1(
1,
b011010000 1
#209000000
b011010001 !
0#
0$
b011010001 %
0'
0(
0,
b011010001 1
03
#210000000
b011010010 !
1#
1$
b011010010 %
1'
1(
1,
b011010010 1
13
#211000000
b011010011 !
b011010011 %
0,
b011010011 1
#212000000
b011010100 !
1#
b011010100 %
1'
1(
1,
b011010100 1
#213000000
b011010101 !
0#
0$
b011010101 %
0'
0(
0,
b011010101 1
03
#214000000
b011010110 !
1#
1$
b011010110 %
1'
1(
1,
b011010110 1
13
#215000000
b011010111 !
b011010111 %
0,
b011010111 1
#216000000
b011011000 !
1#
b011011000 %
1'
1(
1,
b011011000 1
#217000000
b011011001 !
0#
0$
b011011001 %
0'
0(
0,
b011011001 1
03
#218000000
b011011010 !
1#
1$
b011011010 %
1'
1(
1,
b011011010 1
13
#219000000
b011011011 !
b011011011 %
0,
b011011011 1
#220000000
b011011100 !
1#
b011011100 %
1'
1(
1,
b011011100 1
#221000000
b011011101 !
0#
0$
b011011101 %
0'
0(
0,
b011011101 1
03
#222000000
b011011110 !
1#
1$
b011011110 %
1'
1(
1,
b011011110 1
13
#223000000
b011011111 !
b011011111 %
0,
b011011111 1
#224000000
b011100000 !
1#
b011100000 %
1'
1(
0)
1*
1+
1,
1-
1.
10
b011100000 1
#225000000
b011100001 !
0#
0$
b011100001 %
0'
0(
0,
b011100001 1
03
#226000000
b011100010 !
1#
1$
b011100010 %
1'
1(
1,
b011100010 1
13
#227000000
b011100011 !
b011100011 %
0,
b011100011 1
#228000000
b011100100 !
1#
b011100100 %
1'
1(
1)
1,
0-
b011100100 1
#229000000
b011100101 !
0#
0$
b011100101 %
0'
0(
0,
b011100101 1
03
#230000000
b011100110 !
1#
1$
b011100110 %
1'
1(
1,
b011100110 1
13
#231000000
b011100111 !
b011100111 %
0,
b011100111 1
#232000000
b011101000 !
1#
b011101000 %
1'
1(
1,
b011101000 1
#233000000
b011101001 !
0#
0$
b011101001 %
0'
0(
0,
b011101001 1
03
#234000000
b011101010 !
1#
1$
b011101010 %
1'
1(
1,
b011101010 1
13
#235000000
b011101011 !
b011101011 %
0,
b011101011 1
#236000000
b011101100 !
1#
b011101100 %
1'
1(
1,
b011101100 1
#237000000
b011101101 !
0#
0$
b011101101 %
0'
0(
0,
b011101101 1
03
#238000000
b011101110 !
1#
1$
b011101110 %
1'
1(
1,
b011101110 1
13
#239000000
b011101111 !
b011101111 %
0,
b011101111 1
#240000000
b011110000 !
1#
b011110000 %
1'
1(
1,
b011110000 1
#241000000
b011110001 !
0#
0$
b011110001 %
0'
0(
0,
b011110001 1
03
#242000000
b011110010 !
1#
1$
b011110010 %
1'
1(
1,
b011110010 1
13
#243000000
b011110011 !
b011110011 %
0,
b011110011 1
#244000000
b011110100 !
1#
b011110100 %
1'
1(
1,
b011110100 1
#245000000
b011110101 !
0#
0$
b011110101 %
0'
0(
0,
b011110101 1
03
#246000000
b011110110 !
1#
1$
b011110110 %
1'
1(
1,
b011110110 1
13
#247000000
b011110111 !
b011110111 %
0,
b011110111 1
#248000000
b011111000 !
1#
b011111000 %
1'
1(
1,
b011111000 1
#249000000
b011111001 !
0#
0$
b011111001 %
0'
0(
0,
b011111001 1
03
#250000000
b011111010 !
1#
1$
b011111010 %
1'
1(
1,
b011111010 1
13
#251000000
b011111011 !
b011111011 %
0,
b011111011 1
#252000000
b011111100 !
1#
b011111100 %
1'
1(
1,
b011111100 1
#253000000
b011111101 !
0#
0$
b011111101 %
0'
0(
0,
b011111101 1
03
#254000000
b011111110 !
1#
1$
b011111110 %
1'
1(
1,
b011111110 1
13
#255000000
b011111111 !
b011111111 %
0,
b011111111 1
#256000000
b100000000 !
1#
b100000000 %
1'
1(
0*
1+
1,
1-
0.
00
b100000000 1
#257000000
b100000001 !
0#
0$
b100000001 %
0'
0(
0,
b100000001 1
03
#258000000
b100000010 !
1#
1$
b100000010 %
1'
1(
1,
b100000010 1
13
#259000000
b100000011 !
b100000011 %
0,
b100000011 1
#260000000
b100000100 !
1#
b100000100 %
1'
1(
1,
0-
b100000100 1
#261000000
b100000101 !
0#
0$
b100000101 %
0'
0(
0,
b100000101 1
03
#262000000
b100000110 !
1#
1$
b100000110 %
1'
1(
1,
b100000110 1
13
#263000000
b100000111 !
b100000111 %
0,
b100000111 1
#264000000
b100001000 !
1#
b100001000 %
1'
1(
1,
b100001000 1
#265000000
b100001001 !
0#
0$
b100001001 %
0'
0(
0,
b100001001 1
03
#266000000
b100001010 !
1#
1$
b100001010 %
1'
1(
1,
b100001010 1
13
#267000000
b100001011 !
b100001011 %
0,
b100001011 1
#268000000
b100001100 !
1#
b100001100 %
1'
1(
1,
b100001100 1
#269000000
b100001101 !
0#
0$
b100001101 %
0'
0(
0,
b100001101 1
03
#270000000
b100001110 !
1#
1$
b100001110 %
1'
1(
1,
b100001110 1
13
#271000000
b100001111 !
b100001111 %
0,
b100001111 1
#272000000
b100010000 !
1#
b100010000 %
1'
1(
1,
b100010000 1
#273000000
b100010001 !
0#
0$
b100010001 %
0'
0(
0,
b100010001 1
03
#274000000
b100010010 !
1#
1$
b100010010 %
1'
1(
1,
b100010010 1
13
#275000000
b100010011 !
b100010011 %
0,
b100010011 1
#276000000
b100010100 !
1#
b100010100 %
1'
1(
1,
b100010100 1
#277000000
b100010101 !
0#
0$
b100010101 %
0'
0(
0,
b100010101 1
03
#278000000
b100010110 !
1#
1$
b100010110 %
1'
1(
1,
b100010110 1
13
#279000000
b100010111 !
b100010111 %
0,
b100010111 1
#280000000
b100011000 !
1#
b100011000 %
1'
1(
1,
b100011000 1
#281000000
b100011001 !
0#
0$
b100011001 %
0'
0(
0,
b100011001 1
03
#282000000
b100011010 !
1#
1$
b100011010 %
1'
1(
1,
b100011010 1
13
#283000000
b100011011 !
b100011011 %
0,
b100011011 1
#284000000
b100011100 !
1#
b100011100 %
1'
1(
1,
b100011100 1
#285000000
b100011101 !
0#
0$
b100011101 %
0'
0(
0,
b100011101 1
03
#286000000
b100011110 !
1#
1$
b100011110 %
1'
1(
1,
b100011110 1
13
#287000000
b100011111 !
b100011111 %
0,
b100011111 1
#288000000
b100100000 !
1#
b100100000 %
1'
1(
0)
1,
1-
b100100000 1
#289000000
b100100001 !
0#
0$
b100100001 %
0'
0(
0,
b100100001 1
03
#290000000
b100100010 !
1#
1$
b100100010 %
1'
1(
1,
b100100010 1
13
#291000000
b100100011 !
b100100011 %
0,
b100100011 1
#292000000
b100100100 !
1#
b100100100 %
1'
1(
1)
1,
0-
b100100100 1
#293000000
b100100101 !
0#
0$
b100100101 %
0'
0(
0,
b100100101 1
03
#294000000
b100100110 !
1#
1$
b100100110 %
1'
1(
1,
b100100110 1
13
#295000000
b100100111 !
b100100111 %
0,
b100100111 1
#296000000
b100101000 !
1#
b100101000 %
1'
1(
1,
b100101000 1
#297000000
b100101001 !
0#
0$
b100101001 %
0'
0(
0,
b100101001 1
03
#298000000
b100101010 !
1#
1$
b100101010 %
1'
1(
1,
b100101010 1
13
#299000000
b100101011 !
b100101011 %
0,
b100101011 1
#300000000
b100101100 !
1#
b100101100 %
1'
1(
1,
b100101100 1
#301000000
b100101101 !
0#
0$
b100101101 %
0'
0(
0,
b100101101 1
03
#302000000
b100101110 !
1#
1$
b100101110 %
1'
1(
1,
b100101110 1
13
#303000000
b100101111 !
b100101111 %
0,
b100101111 1
#304000000
b100110000 !
1#
b100110000 %
1'
1(
1,
b100110000 1
#305000000
b100110001 !
0#
0$
b100110001 %
0'
0(
0,
b100110001 1
03
#306000000
b100110010 !
1#
1$
b100110010 %
1'
1(
1,
b100110010 1
13
