5to Semestre/arquitecturaDeComputadoras/tarea03-comp-igual/circuito.vhd
library IEEE;
use IEEE.STD_LOGIC_1164.all;

entity comp_igual_3bits is
  port (
    a   : in  STD_LOGIC_VECTOR(2 downto 0);
    b   : in  STD_LOGIC_VECTOR(2 downto 0);
    ig  : out STD_LOGIC
  );
end comp_igual_3bits;

architecture arqui_comp_igual_3bits of comp_igual_3bits is
begin
  ig <= '1' when a = b else '0';
end arqui_comp_igual_3bits;

5to Semestre/arquitecturaDeComputadoras/tarea03-comp-igual/tb_circuito.vhd
library IEEE;
use IEEE.STD_LOGIC_1164.all;
use IEEE.NUMERIC_STD.all;

entity tb_circuito is
end tb_circuito;

architecture t of tb_circuito is
  signal a  : STD_LOGIC_VECTOR(2 downto 0) := (others => '0');
  signal b  : STD_LOGIC_VECTOR(2 downto 0) := (others => '0');
  signal ig : STD_LOGIC;
begin

  uut : entity work.comp_igual_3bits(arqui_comp_igual_3bits)
        port map (a, b, ig);

  stim : process
  begin
    for i in 0 to 7 loop
      for j in 0 to 7 loop
        a <= STD_LOGIC_VECTOR(to_unsigned(i, 3));
        b <= STD_LOGIC_VECTOR(to_unsigned(j, 3));
        wait for 100 ns;
        assert (ig = '1') = (i = j)
          report "Falla con i=" & integer'image(i) & " j=" & integer'image(j)
          severity error;
      end loop;
    end loop;

    report "Listo: 64 combinaciones aplicadas. Abre el .vcd en gtkwave.";
    wait;
  end process;

end t;

5to Semestre/arquitecturaDeComputadoras/tarea03-comp-igual/tb_circuito.vcd
$date
  Mon Sep 14 21:10:03 2026
$end
$version
  GHDL v0
$end
$timescale
  1 fs
$end
$scope module standard $end
$upscope $end
$scope module std_logic_1164 $end
$upscope $end
$scope module numeric_std $end
$upscope $end
$scope module tb_circuito $end
$var reg 3 ! a[2:0] $end
$var reg 3 " b[2:0] $end
$var reg 1 # ig $end
$scope module uut $end
$var reg 3 $ a[2:0] $end
$var reg 3 % b[2:0] $end
$var reg 1 & ig $end
$upscope $end
$upscope $end
$enddefinitions $end
#0
b000 !
b000 "
1#
b000 $
b000 %
1&
#100000000
b001 "
0#
b001 %
0&
#200000000
b010 "
b010 %
#300000000
b011 "
b011 %
#400000000
b100 "
b100 %
#500000000
b101 "
b101 %
#600000000
b110 "
b110 %
#700000000
b111 "
b111 %
#800000000
b001 !
b000 "
b001 $
b000 %
#900000000
b001 "
1#
b001 %
1&
#1000000000
b010 "
0#
b010 %
0&
#1100000000
b011 "
b011 %
#1200000000
b100 "
b100 %
#1300000000
b101 "
b101 %
#1400000000
b110 "
b110 %
#1500000000
b111 "
b111 %
#1600000000
b010 !
b000 "
b010 $
b000 %
#1700000000
b001 "
b001 %
#1800000000
b010 "
1#
b010 %
1&
#1900000000
b011 "
0#
b011 %
0&
#2000000000
b100 "
b100 %
#2100000000
b101 "
b101 %
#2200000000
b110 "
b110 %
#2300000000
b111 "
b111 %
#2400000000
b011 !
b000 "
b011 $
b000 %
#2500000000
b001 "
b001 %
#2600000000
b010 "
b010 %
#2700000000
b011 "
1#
b011 %
1&
#2800000000
b100 "
0#
b100 %
0&
#2900000000
b101 "
b101 %
#3000000000
b110 "
b110 %
#3100000000
b111 "
b111 %
#3200000000
b100 !
b000 "
b100 $
b000 %
#3300000000
b001 "
b001 %
#3400000000
b010 "
b010 %
#3500000000
b011 "
b011 %
#3600000000
b100 "
1#
b100 %
1&
#3700000000
b101 "
0#
b101 %
0&
#3800000000
b110 "
b110 %
#3900000000
b111 "
b111 %
#4000000000
b101 !
b000 "
b101 $
b000 %
#4100000000
b001 "
b001 %
#4200000000
b010 "
b010 %
#4300000000
b011 "
b011 %
#4400000000
b100 "
b100 %
#4500000000
b101 "
1#
b101 %
1&
#4600000000
b110 "
0#
b110 %
0&
#4700000000
b111 "
b111 %
#4800000000
b110 !
b000 "
b110 $
b000 %
#4900000000
b001 "
b001 %
#5000000000
b010 "
b010 %
#5100000000
b011 "
b011 %
#5200000000
b100 "
b100 %
#5300000000
b101 "
b101 %
#5400000000
b110 "
1#
b110 %
1&
#5500000000
b111 "
0#
b111 %
0&
#5600000000
b111 !
b000 "
b111 $
b000 %
#5700000000
b001 "
b001 %
#5800000000
b010 "
b010 %
#5900000000
b011 "
b011 %
#6000000000
b100 "
b100 %
#6100000000
b101 "
b101 %
#6200000000
b110 "
b110 %
#6300000000
b111 "
1#
b111 %
1&
