5to Semestre/arquitecturaDeComputadoras/plantilla/circuito.vhd
-- PLANTILLA de circuito. Lo unico que cambias practica a practica:
--   1. el nombre de la entity (aqui "circuito"),
--   2. las entradas/salidas del port,
--   3. las lineas de logica entre begin y end.
library IEEE;
use IEEE.STD_LOGIC_1164.all;

entity circuito is
  port (
    A, B, C : in  STD_LOGIC;   -- entradas: agrega o quita segun tu practica
    F       : out STD_LOGIC    -- salidas
  );
end circuito;

architecture logica of circuito is
begin
  -- TU LOGICA AQUI. Cada linea es una compuerta o una expresion:
  --   F <= A and B;                  -- AND
  --   F <= A or B;                   -- OR
  --   F <= not A;                    -- inversor
  --   F <= A nand B;                 -- NAND
  --   F <= (not A and not B) or C;   -- combinacion
  F <= (not A and not B) or C;  -- REEMPLAZA por la de tu practica
end logica;

5to Semestre/arquitecturaDeComputadoras/plantilla/tb_circuito.vhd
-- PLANTILLA de testbench. Casi no la tocas: solo actualizas las senales
-- del port map y el numero de combinaciones (2^entradas).
-- Su trabajo: meterle todas las combinaciones a tu circuito y grabar la
-- onda en el .vcd para verla en GTKWave.
library IEEE;
use IEEE.STD_LOGIC_1164.all;
use IEEE.NUMERIC_STD.all;  -- para to_unsigned (convertir numero -> bits)

entity tb_circuito is
end tb_circuito;             -- el nombre que va en: ghdl -e tb_circuito

architecture t of tb_circuito is
  -- Mismas senales que el port de tu circuito, en el mismo orden.
  signal A, B, C : STD_LOGIC := '0';  -- := '0' evita el 'U' del arranque
  signal F       : STD_LOGIC;
begin

  -- Instancia tu circuito: uut = "unit under test".
  -- "work.circuito(logica)" = entity circuito, architecture logica.
  uut : entity work.circuito(logica) port map (A, B, C, F);

  stim : process
    variable v : STD_LOGIC_VECTOR(2 downto 0);  -- aqui caben A,B,C
  begin
    -- Recorre las 2^3 = 8 combinaciones: 000,001,...,111.
    -- Para 4 entradas: 0 to 15 y STD_LOGIC_VECTOR(3 downto 0).
    for i in 0 to 7 loop
      v  := STD_LOGIC_VECTOR(to_unsigned(i, 3));  -- i en binario
      A  <= v(2);  B <= v(1);  C <= v(0);         -- parte el bus en bits
      wait for 100 ns;  -- deja pasar tiempo para que se vea en la onda
    end loop;

    report "Listo: 8 combinaciones aplicadas. Abre el .vcd en gtkwave.";
    wait;  -- el process se queda quieto; sin esto reiniciaria para siempre
  end process;

end t;

5to Semestre/arquitecturaDeComputadoras/plantilla/tb_circuito.vcd
$date
  Fri Sep 11 21:42:42 2026
$end
$version
  GHDL v0
$end
$timescale
  1 fs
$end
$scope module standard $end
$upscope $end
$scope module std_logic_1164 $end
$upscope $end
$scope module numeric_std $end
$upscope $end
$scope module tb_circuito $end
$var reg 1 ! a $end
$var reg 1 " b $end
$var reg 1 # c $end
$var reg 1 $ f $end
$scope module uut $end
$var reg 1 % a $end
$var reg 1 & b $end
$var reg 1 ' c $end
$var reg 1 ( f $end
$upscope $end
$upscope $end
$enddefinitions $end
#0
0!
0"
0#
1$
0%
0&
0'
1(
#100000000
1#
1'
#200000000
1"
0#
0$
1&
0'
0(
#300000000
1#
1$
1'
1(
#400000000
1!
0"
0#
0$
1%
0&
0'
0(
#500000000
1#
1$
1'
1(
#600000000
1"
0#
0$
1&
0'
0(
#700000000
1#
1$
1'
1(
