5to Semestre/arquitecturaDeComputadoras/practica05/circuito.vhd
-- Corrimientos de 4 bits controlados por ctrl (0..3), la logica copiada
-- del profe (con relleno '0' en el desplazamiento):
--   sal  via when/else, salW via with/select,
--   salC via case, salI via if/elsif. Las 4 deben dar la misma onda.
library IEEE;
use IEEE.STD_LOGIC_1164.all;

entity shift_wci_23400357 is
  port (
    ent  : in  STD_LOGIC_VECTOR(3 downto 0);
    ctrl : in  STD_LOGIC_VECTOR(1 downto 0);
    sal  : out STD_LOGIC_VECTOR(3 downto 0);  -- via when/else
    salC : out STD_LOGIC_VECTOR(3 downto 0);  -- via case
    salI : out STD_LOGIC_VECTOR(3 downto 0);  -- via if
    salW : out STD_LOGIC_VECTOR(3 downto 0)   -- via with/select
  );
end shift_wci_23400357;

architecture arqui_shift_wci of shift_wci_23400357 is
begin

  -- estructura condicional concurrente WHEN (sal)
  sal <= (ent)                          when (ctrl = "00") else
         ('0' & ent(3 downto 1))        when (ctrl = "01") else
         (ent(2 downto 0) & '0')        when (ctrl = "10") else
         (ent(0) & ent(1) & ent(2) & ent(3)) when (ctrl = "11") else
         "----";

  -- estructura condicional concurrente WITH (salW)
  with ctrl select
    salW <= (ent)                       when "00",
            ('0' & ent(3 downto 1))     when "01",
            (ent(2 downto 0) & '0')     when "10",
            (ent(0) & ent(1) & ent(2) & ent(3)) when "11",
            "----" when others;

  -- estructura secuencial CASE dentro de process (salC)
  process (ent, ctrl)
  begin
    case ctrl is
      when "00" =>
        salC <= ent;
      when "01" =>
        salC <= '0' & ent(3 downto 1);
      when "10" =>
        salC <= ent(2 downto 0) & '0';
      when "11" =>
        salC <= ent(0) & ent(1) & ent(2) & ent(3);
      when others =>
        salC <= "----";
    end case;
  end process;

  -- estructura secuencial IF dentro de process (salI)
  process (ent, ctrl)
  begin
    if (ctrl = "00") then
      salI <= ent;
    elsif (ctrl = "01") then
      salI <= '0' & ent(3 downto 1);
    elsif (ctrl = "10") then
      salI <= ent(2 downto 0) & '0';
    elsif (ctrl = "11") then
      salI <= ent(0) & ent(1) & ent(2) & ent(3);
    else
      salI <= "----";
    end if;
  end process;
end arqui_shift_wci;

5to Semestre/arquitecturaDeComputadoras/practica05/tb_circuito.vhd
-- Testbench: ent = "1011" constante, ctrl recorre 0..3.
library IEEE;
use IEEE.STD_LOGIC_1164.all;
use IEEE.NUMERIC_STD.all;

entity tb_circuito is
end tb_circuito;

architecture t of tb_circuito is
  signal ent  : STD_LOGIC_VECTOR(3 downto 0) := "1011";
  signal ctrl : STD_LOGIC_VECTOR(1 downto 0) := (others => '0');
  signal sal, salC, salI, salW : STD_LOGIC_VECTOR(3 downto 0);
begin

  uut : entity work.shift_wci_23400357(arqui_shift_wci)
        port map (ent, ctrl, sal, salC, salI, salW);

  stim : process
    variable i : natural := 0;
  begin
    -- Estimulo INFINITO: ctrl 0..3 reciclando cada 100 ns, para siempre.
    -- La duracion de la simulacion la decide quien corre ./run.sh.
    loop
      ctrl <= STD_LOGIC_VECTOR(to_unsigned(i mod 4, 2));
      wait for 100 ns;
      i := i + 1;
    end loop;
  end process;

end t;

5to Semestre/arquitecturaDeComputadoras/practica05/tb_circuito.vcd
$date
  Sat Sep 12 17:02:09 2026
$end
$version
  GHDL v0
$end
$timescale
  1 fs
$end
$scope module standard $end
$upscope $end
$scope module textio $end
$upscope $end
$scope module std_logic_1164 $end
$upscope $end
$scope module numeric_std $end
$upscope $end
$scope module tb_circuito $end
$var reg 4 ! ent[3:0] $end
$var reg 2 " ctrl[1:0] $end
$var reg 4 # sal[3:0] $end
$var reg 4 $ salc[3:0] $end
$var reg 4 % sali[3:0] $end
$var reg 4 & salw[3:0] $end
$scope module uut $end
$var reg 4 ' ent[3:0] $end
$var reg 2 ( ctrl[1:0] $end
$var reg 4 ) sal[3:0] $end
$var reg 4 * salc[3:0] $end
$var reg 4 + sali[3:0] $end
$var reg 4 , salw[3:0] $end
$upscope $end
$upscope $end
$enddefinitions $end
#0
b1011 !
b00 "
b1011 #
b1011 $
b1011 %
b1011 &
b1011 '
b00 (
b1011 )
b1011 *
b1011 +
b1011 ,
#100000000
b01 "
b0101 #
b0101 $
b0101 %
b0101 &
b01 (
b0101 )
b0101 *
b0101 +
b0101 ,
#200000000
b10 "
b0110 #
b0110 $
b0110 %
b0110 &
b10 (
b0110 )
b0110 *
b0110 +
b0110 ,
#300000000
b11 "
b1101 #
b1101 $
b1101 %
b1101 &
b11 (
b1101 )
b1101 *
b1101 +
b1101 ,
#400000000
b00 "
b1011 #
b1011 $
b1011 %
b1011 &
b00 (
b1011 )
b1011 *
b1011 +
b1011 ,
#500000000
b01 "
b0101 #
b0101 $
b0101 %
b0101 &
b01 (
b0101 )
b0101 *
b0101 +
b0101 ,
#600000000
b10 "
b0110 #
b0110 $
b0110 %
b0110 &
b10 (
b0110 )
b0110 *
b0110 +
b0110 ,
#700000000
b11 "
b1101 #
b1101 $
b1101 %
b1101 &
b11 (
b1101 )
b1101 *
b1101 +
b1101 ,
#800000000
b00 "
b1011 #
b1011 $
b1011 %
b1011 &
b00 (
b1011 )
b1011 *
b1011 +
b1011 ,
#900000000
b01 "
b0101 #
b0101 $
b0101 %
b0101 &
b01 (
b0101 )
b0101 *
b0101 +
b0101 ,
#1000000000
b10 "
b0110 #
b0110 $
b0110 %
b0110 &
b10 (
b0110 )
b0110 *
b0110 +
b0110 ,
