5to Semestre/arquitecturaDeComputadoras/practica03-circuito-nand/circuito.vhd
-- Practica 3: circuito del diagrama (3 entradas A,B,C -> 1 salida F).
--
-- El diagrama tiene:
--   2 inversores alimentando una NAND  -> g1 = (A'B')'
--   esa NAND con C' en otra NAND       -> g2 = ((A'B')' * C')'
--   una AND de 3 entradas              -> g3 = A*B*C
--   y un OR final: F = g2 + g3
--
-- Simplificacion (De Morgan + absorcion):
--   F = ((A'B')' * C')' + ABC
--     = (A'B') + C + ABC        (De Morgan en el primer termino)
--     = A'B' + C                (C absorbe a ABC: C + C*AB = C)
--
-- O sea todo el circuito se reduce a: F = A'B' + C = (A+B)' + C
-- F vale 1 cuando C=1, o cuando A y B son 0 a la vez.
library IEEE;
use IEEE.STD_LOGIC_1164.all;

entity circuito is
  port (
    A, B, C : in  STD_LOGIC;
    F       : out STD_LOGIC
  );
end circuito;

-- ESTILO 1: tal cual el diagrama, compuerta por compuerta.
architecture estructural of circuito is
  signal nA, nB, nC : STD_LOGIC;
  signal g1, g2, g3 : STD_LOGIC;
begin
  nA <= not A;
  nB <= not B;
  nC <= not C;

  g1 <= nA nand nB;       -- (A'B')'
  g2 <= g1 nand nC;       -- ((A'B')' * C')'
  g3 <= A and B and C;    -- ABC

  F <= g2 or g3;
end estructural;

-- ESTILO 2: la version simplificada (2 compuertas: NOR + OR).
architecture simplificada of circuito is
begin
  F <= (not A and not B) or C;
end simplificada;

5to Semestre/arquitecturaDeComputadoras/practica03-circuito-nand/tb_circuito.vhd
-- Testbench: recorre las 8 combinaciones de ABC y verifica que el circuito
-- original (estructural) y el simplificado den EXACTAMENTE lo mismo.
-- Si alguna fila no coincide, la simulacion se detiene con error.
library IEEE;
use IEEE.STD_LOGIC_1164.all;

entity tb_circuito is
end tb_circuito;

architecture t of tb_circuito is
  signal A, B, C : STD_LOGIC := '0';  -- := evita el 'U' del arranque
  signal F1, F2  : STD_LOGIC;
begin

  u_orig : entity work.circuito(estructural)   port map (A, B, C, F1);
  u_simp : entity work.circuito(simplificada) port map (A, B, C, F2);

  stim : process
    -- las 8 filas de la tabla de verdad, en orden 000..111
    type tabla_t is array (0 to 7) of STD_LOGIC_VECTOR(2 downto 0);
    constant casos : tabla_t := ("000","001","010","011","100","101","110","111");
    -- respuesta esperada de F = A'B' + C
    type resp_t   is array (0 to 7) of STD_LOGIC;
    constant esp  : resp_t := ('1','1','0','1','0','1','0','1');
  begin
    for i in casos'range loop
      A <= casos(i)(2); B <= casos(i)(1); C <= casos(i)(0);
      wait for 100 ns;
      assert (F1 = esp(i)) and (F2 = esp(i))
        report "FALLA en ABC=" & STD_LOGIC'image(casos(i)(2))
             & STD_LOGIC'image(casos(i)(1))
             & STD_LOGIC'image(casos(i)(0))
        severity failure;
    end loop;

    report "OK: las 8 filas coinciden. F = A'B' + C verificado.";
    wait;
  end process;

end t;

5to Semestre/arquitecturaDeComputadoras/practica03-circuito-nand/tb_circuito.vcd
$date
  Fri Sep 11 21:53:48 2026
$end
$version
  GHDL v0
$end
$timescale
  1 fs
$end
$scope module standard $end
$upscope $end
$scope module std_logic_1164 $end
$upscope $end
$scope module tb_circuito $end
$var reg 1 ! a $end
$var reg 1 " b $end
$var reg 1 # c $end
$var reg 1 $ f1 $end
$var reg 1 % f2 $end
$scope module u_orig $end
$var reg 1 & a $end
$var reg 1 ' b $end
$var reg 1 ( c $end
$var reg 1 ) f $end
$var reg 1 * na $end
$var reg 1 + nb $end
$var reg 1 , nc $end
$var reg 1 - g1 $end
$var reg 1 . g2 $end
$var reg 1 / g3 $end
$upscope $end
$scope module u_simp $end
$var reg 1 0 a $end
$var reg 1 1 b $end
$var reg 1 2 c $end
$var reg 1 3 f $end
$upscope $end
$upscope $end
$enddefinitions $end
#0
0!
0"
0#
1$
1%
0&
0'
0(
1)
1*
1+
1,
0-
1.
0/
00
01
02
13
#100000000
1#
1(
0,
12
#200000000
1"
0#
0$
0%
1'
0(
0)
0+
1,
1-
0.
11
02
03
#300000000
1#
1$
1%
1(
1)
0,
1.
12
13
#400000000
1!
0"
0#
0$
0%
1&
0'
0(
0)
0*
1+
1,
0.
10
01
02
03
#500000000
1#
1$
1%
1(
1)
0,
1.
12
13
#600000000
1"
0#
0$
0%
1'
0(
0)
0+
1,
0.
11
02
03
#700000000
1#
1$
1%
1(
1)
0,
1.
1/
12
13
