5to Semestre/arquitecturaDeComputadoras/practica06/circuito.vhd
-- Tabla de verdad del profe: entra x[2:0], sale y[1:0].
--   x=000->01, 011->01, 110->01 : y=01
--   x=001->11, 111->11          : y=11
--   x=010->00                   : y=00
--   x=100->10, 101->10          : y=10
-- Mismas 8 filas, una salida por estructura: when, with, case, if.
library IEEE;
use IEEE.STD_LOGIC_1164.all;

entity tabla_wwci_23400357 is
  port (
    x  : in  STD_LOGIC_VECTOR(2 downto 0);
    y1 : out STD_LOGIC_VECTOR(1 downto 0);  -- via when/else
    y2 : out STD_LOGIC_VECTOR(1 downto 0);  -- via with/select
    y3 : out STD_LOGIC_VECTOR(1 downto 0);  -- via case
    y4 : out STD_LOGIC_VECTOR(1 downto 0)   -- via if
  );
end tabla_wwci_23400357;

architecture arqui_tabla of tabla_wwci_23400357 is
begin

  -- estructura condicional concurrente WHEN (y1)
  y1 <= "01" when (x = "000" or x = "011" or x = "110") else
        "11" when (x = "001" or x = "111") else
        "00" when (x = "010") else
        "10" when (x = "100" or x = "101") else
        "--";

  -- estructura de seleccion concurrente WITH (y2)
  with x select
    y2 <= "01" when "000",
          "11" when "001",
          "00" when "010",
          "01" when "011",
          "10" when "100",
          "10" when "101",
          "01" when "110",
          "11" when "111",
          "--" when others;

  -- estructura secuencial CASE dentro de process (y3)
  process (x)
  begin
    case x is
      when "000" => y3 <= "01";
      when "001" => y3 <= "11";
      when "010" => y3 <= "00";
      when "011" => y3 <= "01";
      when "100" => y3 <= "10";
      when "101" => y3 <= "10";
      when "110" => y3 <= "01";
      when "111" => y3 <= "11";
      when others => y3 <= "--";
    end case;
  end process;

  -- estructura secuencial IF dentro de process (y4)
  process (x)
  begin
    if (x = "000" or x = "011" or x = "110") then
      y4 <= "01";
    elsif (x = "001" or x = "111") then
      y4 <= "11";
    elsif (x = "010") then
      y4 <= "00";
    else
      y4 <= "10";
    end if;
  end process;
end arqui_tabla;

5to Semestre/arquitecturaDeComputadoras/practica06/tb_circuito.vhd
-- Testbench: barre las 8 combinaciones de x y COMPRUEBA contra la tabla.
-- Si alguna fila no coincide, rompe con error (asi el circuito se
-- autoverifica, no depende de que leas bien la onda).
library IEEE;
use IEEE.STD_LOGIC_1164.all;
use IEEE.NUMERIC_STD.all;

entity tb_circuito is
end tb_circuito;

architecture t of tb_circuito is
  signal x : STD_LOGIC_VECTOR(2 downto 0) := (others => '0');
  signal y1, y2, y3, y4 : STD_LOGIC_VECTOR(1 downto 0);
begin

  uut : entity work.tabla_wwci_23400357(arqui_tabla)
        port map (x, y1, y2, y3, y4);

  stim : process
    type t_tab is array (0 to 7) of STD_LOGIC_VECTOR(1 downto 0);
    constant ESPERA : t_tab := ("01", "11", "00", "01",
                                "10", "10", "01", "11");
    variable ok : boolean := true;
  begin
    for i in 0 to 7 loop
      x <= STD_LOGIC_VECTOR(to_unsigned(i, 3));
      wait for 10 ns;
      -- Las 4 estructuras deben dar lo mismo; se checa la when (y1)
      -- y ademas que todas coincidan entre si.
      assert y1 = ESPERA(i)
        report "Fila " & integer'image(i)
             & ": salio " & to_string(y1)
             & ", esperaba " & to_string(ESPERA(i))
        severity error;
      if y1 /= ESPERA(i) then
        ok := false;
      end if;
      assert (y1 = y2) and (y1 = y3) and (y1 = y4)
        report "Fila " & integer'image(i) & ": las 4 salidas difieren"
        severity error;
    end loop;

    assert ok report "La tabla NO coincide." severity failure;
    report "Tabla verificada: 8 de 8 filas correctas.";
    wait;
  end process;

end t;

5to Semestre/arquitecturaDeComputadoras/practica06/tb_circuito.vcd
$date
  Sat Sep 12 17:56:20 2026
$end
$version
  GHDL v0
$end
$timescale
  1 fs
$end
$scope module standard $end
$upscope $end
$scope module textio $end
$upscope $end
$scope module std_logic_1164 $end
$upscope $end
$scope module numeric_std $end
$upscope $end
$scope module tb_circuito $end
$var reg 3 ! x[2:0] $end
$var reg 2 " y1[1:0] $end
$var reg 2 # y2[1:0] $end
$var reg 2 $ y3[1:0] $end
$var reg 2 % y4[1:0] $end
$scope module uut $end
$var reg 3 & x[2:0] $end
$var reg 2 ' y1[1:0] $end
$var reg 2 ( y2[1:0] $end
$var reg 2 ) y3[1:0] $end
$var reg 2 * y4[1:0] $end
$upscope $end
$upscope $end
$enddefinitions $end
#0
b000 !
b01 "
b01 #
b01 $
b01 %
b000 &
b01 '
b01 (
b01 )
b01 *
#10000000
b001 !
b11 "
b11 #
b11 $
b11 %
b001 &
b11 '
b11 (
b11 )
b11 *
#20000000
b010 !
b00 "
b00 #
b00 $
b00 %
b010 &
b00 '
b00 (
b00 )
b00 *
#30000000
b011 !
b01 "
b01 #
b01 $
b01 %
b011 &
b01 '
b01 (
b01 )
b01 *
#40000000
b100 !
b10 "
b10 #
b10 $
b10 %
b100 &
b10 '
b10 (
b10 )
b10 *
#50000000
b101 !
b101 &
#60000000
b110 !
b01 "
b01 #
b01 $
b01 %
b110 &
b01 '
b01 (
b01 )
b01 *
#70000000
b111 !
b11 "
b11 #
b11 $
b11 %
b111 &
b11 '
b11 (
b11 )
b11 *
